fluc_rs/__init__.py
fluc_rs/fluc_rs.cp314-win_amd64.pyd
fluctuoscopy-0.2.1.dist-info/METADATA
fluctuoscopy-0.2.1.dist-info/WHEEL
fluctuoscopy-0.2.1.dist-info/licenses/LICENSE
fluctuoscopy/__init__.py
fluctuoscopy/bin/FSCOPE_linux
fluctuoscopy/bin/FSCOPE_mac
fluctuoscopy/bin/FSCOPE_windows.exe
fluctuoscopy/bin/LICENSE
fluctuoscopy/bin/fluctuoscope_extC.dll
fluctuoscopy/bin/fluctuoscope_extC.dylib
fluctuoscopy/bin/fluctuoscope_extC.so
fluctuoscopy/fluctuosco.py
fluctuoscopy/tests/__init__.py
fluctuoscopy/tests/test_fscopy.py
fluctuoscopy-0.2.1.dist-info/RECORD
