Metadata-Version: 2.4
Name: fluctuoscopy
Version: 0.2.1
Classifier: Programming Language :: Rust
Classifier: Programming Language :: Python :: Implementation :: CPython
Classifier: Programming Language :: Python :: Implementation :: PyPy
Requires-Dist: numpy
Requires-Dist: maturin ; extra == 'dev'
Requires-Dist: pytest ; extra == 'dev'
Provides-Extra: dev
License-File: LICENSE
Summary: A Python wrapper with extras for the FSCOPE program, written by Andreas Glatz
Author: Graham Kimbell, Ulderico Filippozzi, Andreas Glatz
License: MIT AND BSD-2-CLAUSE
Requires-Python: >=3.9
